nuitka_setuptools.py
nuitka_setuptools-2.0.dist-info/DESCRIPTION.rst
nuitka_setuptools-2.0.dist-info/METADATA
nuitka_setuptools-2.0.dist-info/RECORD
nuitka_setuptools-2.0.dist-info/WHEEL
nuitka_setuptools-2.0.dist-info/metadata.json
nuitka_setuptools-2.0.dist-info/top_level.txt
