Metadata-Version: 2.0
Name: nuitka-setuptools
Version: 2.0
Summary: Extension to setuptools to run your package through nuitka to produce compiled, faster, obfuscated binary modules.
Home-page: https://gitlab.com/alelec/nuitka-setuptools
Author: Andrew Leech
Author-email: andrew@alelec.net
License: UNKNOWN
Platform: UNKNOWN
Requires-Dist: setuptools-scm
Requires-Dist: nuitka
